iso8601/__init__.py
iso8601/iso8601.py
iso8601/py.typed
iso8601/test_iso8601.py
iso8601-1.0.1.dist-info/LICENSE
iso8601-1.0.1.dist-info/WHEEL
iso8601-1.0.1.dist-info/METADATA
iso8601-1.0.1.dist-info/RECORD
