Metadata-Version: 2.1
Name: iso8601
Version: 1.0.1
Summary: Simple module to parse ISO 8601 dates
Home-page: https://github.com/micktwomey/pyiso8601
License: MIT
Author: Michael Twomey
Author-email: mick@twomeylee.name
Requires-Python: >=3.6.2,<4.0
Classifier: License :: OSI Approved :: MIT License
Classifier: Programming Language :: Python :: 3
Classifier: Programming Language :: Python :: 3.10
Classifier: Programming Language :: Python :: 3.7
Classifier: Programming Language :: Python :: 3.8
Classifier: Programming Language :: Python :: 3.9
Project-URL: Documentation, https://pyiso8601.readthedocs.io/en/latest/
Project-URL: Repository, https://github.com/micktwomey/pyiso8601
